omni_archive/__init__.py
omni_archive/_version.py
omni_archive/dir.py
omni_archive/generic.py
omni_archive/tar.py
omni_archive/zip.py
omni_archive-0.0.2.dist-info/LICENSE
omni_archive-0.0.2.dist-info/METADATA
omni_archive-0.0.2.dist-info/WHEEL
omni_archive-0.0.2.dist-info/top_level.txt
omni_archive-0.0.2.dist-info/RECORD
