Metadata-Version: 2.1
Name: omni_archive
Version: 0.0.2
Summary: A generic archive reader and writer for various archive formats.
Home-page: https://github.com/moi90/omni_archive
Author: Simon-Martin Schroeder
Author-email: sms@informatik.uni-kiel.de
Classifier: Programming Language :: Python :: 3
Classifier: Programming Language :: Python :: 3.8
Classifier: Programming Language :: Python :: 3.9
Classifier: Programming Language :: Python :: 3.10
Classifier: Programming Language :: Python :: 3.11
Classifier: License :: OSI Approved :: GNU General Public License v3 (GPLv3)
Classifier: Operating System :: OS Independent
Classifier: Development Status :: 3 - Alpha
Classifier: Intended Audience :: Science/Research
Requires-Python: >=3.8
License-File: LICENSE
Requires-Dist: pathlib-abc
Requires-Dist: fnmatch2
Provides-Extra: dev
Requires-Dist: black ; extra == 'dev'
Provides-Extra: docs
Requires-Dist: sphinx >=1.4 ; extra == 'docs'
Requires-Dist: sphinx-rtd-theme ; extra == 'docs'
Requires-Dist: sphinx-autodoc-typehints >=1.10.0 ; extra == 'docs'
Provides-Extra: test
Requires-Dist: pytest ; extra == 'test'
Requires-Dist: pytest-cov ; extra == 'test'
